LICENSE.txt
MANIFEST.in
README.rst
requirements.txt
setup.py
clf/__init__.py
clf/api.py
clf/command.py
clf/constants.py
clf/exceptions.py
clf.egg-info/PKG-INFO
clf.egg-info/SOURCES.txt
clf.egg-info/dependency_links.txt
clf.egg-info/entry_points.txt
clf.egg-info/requires.txt
clf.egg-info/top_level.txt